MANIFEST.in
README.rst
setup.py
wsgissi.py
wsgissi.egg-info/PKG-INFO
wsgissi.egg-info/SOURCES.txt
wsgissi.egg-info/dependency_links.txt
wsgissi.egg-info/not-zip-safe
wsgissi.egg-info/requires.txt
wsgissi.egg-info/top_level.txt