Metadata-Version: 1.1
Name: wsgissi
Version: 0.7
Summary: WSGI middleware to process nginx compatible ssi
Home-page: https://github.com/baverman/wsgissi/
Author: Anton Bobrov
Author-email: baverman@gmail.com
License: MIT
Platform: any
Classifier: Development Status :: 4 - Beta
Classifier: Intended Audience :: Developers
Classifier: Intended Audience :: Information Technology
Classifier: Intended Audience :: System Administrators
Classifier: License :: OSI Approved :: MIT License
Classifier: Operating System :: POSIX
Classifier: Operating System :: MacOS
Classifier: Operating System :: Unix
Classifier: Programming Language :: Python
Classifier: Programming Language :: Python :: 2
Classifier: Topic :: Software Development :: Libraries :: Python Modules
Classifier: Topic :: Internet
Classifier: Topic :: Scientific/Engineering
Classifier: Topic :: System :: Distributed Computing
Classifier: Topic :: System :: Systems Administration
Classifier: Topic :: System :: Monitoring
